dev_pipeline_bootstrap-0.4.0.dist-info/DESCRIPTION.rst
dev_pipeline_bootstrap-0.4.0.dist-info/METADATA
dev_pipeline_bootstrap-0.4.0.dist-info/RECORD
dev_pipeline_bootstrap-0.4.0.dist-info/WHEEL
dev_pipeline_bootstrap-0.4.0.dist-info/entry_points.txt
dev_pipeline_bootstrap-0.4.0.dist-info/metadata.json
dev_pipeline_bootstrap-0.4.0.dist-info/top_level.txt
devpipeline_bootstrap/__init__.py
devpipeline_bootstrap/bootstrap.py
