Metadata-Version: 2.0
Name: dev-pipeline-bootstrap
Version: 0.4.0
Summary: build tooling for dev-pipeline
Home-page: https://github.com/dev-pipeline/dev-pipeline-bootstrap
Author: Stephen Newell
Author-email: UNKNOWN
License: BSD-2
Platform: UNKNOWN
Classifier: Development Status :: 2 - Pre-Alpha
Classifier: Environment :: Plugins
Classifier: Intended Audience :: Developers
Classifier: License :: OSI Approved :: BSD License
Classifier: Topic :: Software Development
Classifier: Topic :: Software Development :: Build Tools
Classifier: Topic :: Software Development :: Version Control
Classifier: Topic :: Utilities
Requires-Dist: dev-pipeline-build (>=0.4.0)
Requires-Dist: dev-pipeline-configure (>=0.4.0)
Requires-Dist: dev-pipeline-core (>=0.4.0)
Requires-Dist: dev-pipeline-scm (>=0.4.0)
